percylib/__init__.py
percylib/helpers.py
percylib/specialties.py
percylib/stata.py
percylib-0.5.1.dist-info/METADATA
percylib-0.5.1.dist-info/WHEEL
percylib-0.5.1.dist-info/RECORD
