Metadata-Version: 2.4
Name: percylib
Version: 0.5.1
Summary: Helpers to be paired with the Percy AI VS Code extension.
Author-email: Kevin Bi <kevin@percivaltech.com>
License: MIT
Requires-Python: >=3.9
Requires-Dist: stata-setup>=0.1.3
